aicore/__init__.py
aicore/_version.py
aicore/ml/__init__.py
aicore/ml/data.py
aicore/ml/plot.py
aicore/ml/graph/__init__.py
aicore/ml/graph/_graph.py
aicore/ml/graph/_operations.py
aicore/ml/graph/_parameter.py
aicore/ml/graph/models.py
aicore/ml/graph/optimizers.py
aicore-0.0.3.dist-info/METADATA
aicore-0.0.3.dist-info/WHEEL
aicore-0.0.3.dist-info/top_level.txt
aicore-0.0.3.dist-info/RECORD
