Metadata-Version: 2.1
Name: aicore
Version: 0.0.3
Summary: Library for CoreAI courses (https://www.theaicore.com/)
Home-page: https://www.theaicore.com/
Author: theaicore
Author-email: admissions@theaicore.com
License: UNKNOWN
Project-URL: Website, https://www.theaicore.com/
Keywords: theaicore aicore course machine learning deep learning
Platform: UNKNOWN
Classifier: Development Status :: 2 - Pre-Alpha
Classifier: Programming Language :: Python
Classifier: Programming Language :: Python :: 3
Classifier: Programming Language :: Python :: 3.6
Classifier: Programming Language :: Python :: 3.7
Classifier: Intended Audience :: Developers
Classifier: Operating System :: OS Independent
Classifier: Topic :: Scientific/Engineering
Classifier: Topic :: Software Development :: Libraries
Classifier: Topic :: Scientific/Engineering :: Artificial Intelligence
Classifier: Topic :: Software Development :: Libraries :: Python Modules
Requires-Python: >=3.6
Requires-Dist: numpy (>=1.19.4)
Requires-Dist: scikit-learn (>=0.23.2)
